odoo/addons/l10n_th_account_asset_management/README.rst
odoo/addons/l10n_th_account_asset_management/__init__.py
odoo/addons/l10n_th_account_asset_management/__manifest__.py
odoo/addons/l10n_th_account_asset_management/data/account_asset_parent_data.xml
odoo/addons/l10n_th_account_asset_management/data/account_asset_sub_state_data.xml
odoo/addons/l10n_th_account_asset_management/i18n/l10n_th_account_asset_management.pot
odoo/addons/l10n_th_account_asset_management/models/__init__.py
odoo/addons/l10n_th_account_asset_management/models/account_asset.py
odoo/addons/l10n_th_account_asset_management/models/account_asset_line.py
odoo/addons/l10n_th_account_asset_management/models/account_asset_parent.py
odoo/addons/l10n_th_account_asset_management/models/account_asset_sub_state.py
odoo/addons/l10n_th_account_asset_management/models/account_move.py
odoo/addons/l10n_th_account_asset_management/readme/CONTRIBUTORS.rst
odoo/addons/l10n_th_account_asset_management/readme/DESCRIPTION.rst
odoo/addons/l10n_th_account_asset_management/report/__init__.py
odoo/addons/l10n_th_account_asset_management/report/account_asset_report_xls.py
odoo/addons/l10n_th_account_asset_management/security/ir.model.access.csv
odoo/addons/l10n_th_account_asset_management/static/description/icon.png
odoo/addons/l10n_th_account_asset_management/static/description/index.html
odoo/addons/l10n_th_account_asset_management/tests/__init__.py
odoo/addons/l10n_th_account_asset_management/tests/test_account_asset_management.py
odoo/addons/l10n_th_account_asset_management/tests/test_asset_management_xls.py
odoo/addons/l10n_th_account_asset_management/views/account_asset_parent_views.xml
odoo/addons/l10n_th_account_asset_management/views/account_asset_sub_state_views.xml
odoo/addons/l10n_th_account_asset_management/views/account_asset_views.xml
odoo/addons/l10n_th_account_asset_management/wizard/__init__.py
odoo/addons/l10n_th_account_asset_management/wizard/account_asset_remove.py
odoo_addon_l10n_th_account_asset_management-16.0.1.0.0.1.dist-info/METADATA
odoo_addon_l10n_th_account_asset_management-16.0.1.0.0.1.dist-info/WHEEL
odoo_addon_l10n_th_account_asset_management-16.0.1.0.0.1.dist-info/top_level.txt
odoo_addon_l10n_th_account_asset_management-16.0.1.0.0.1.dist-info/RECORD
